Workbook

Sheet App
A1: 📊 SIMULADOR DE INVESTIMENTOS EM FUNDOS IMOBILIÁRIOS
A2: Aporte mensal, patrimônio projetado e divisão por perfil de investidor
A3: Células azuis = você edita. Células cinzas = cálculo automático, não edite.
B5: CONFIGURAÇÕES
B6: Salário mensal (R$) | D6: 3500
B7: Rendimento da carteira (% a.m.) | D7: 0.0095
B8: Sugestão de aporte (30% do salário) | D8: =salario*30% -> 1050
B10: SIMULE SEU APORTE
B11: 1) Quanto investir por mês? (R$) | D11: 300
B12: 2) Por quantos anos? | D12: 8
B13: 3) Taxa de rendimento mensal (%)? | D13: 0.0095
B14: 4) Patrimônio acumulado (R$) | D14: =FV(taxa_mensal,anos*12,aporte*-1) -> 46692.738
B15: 5) Dividendos mensais estimados (R$) | D15: =patrimonio*rendimento_carteira -> 443.58101
B17: CENÁRIOS DE LONGO PRAZO
A18: Anos | B18: Cenário | C18: Patrimônio (R$) | D18: Dividendo mensal (R$)
A19: 2 | B19: Quanto em 2 anos? | C19: =FV(taxa_mensal,A19*12,aporte*-1) -> 8044.24 | D19: =C19*rendimento_carteira -> 76.42028
A20: 5 | B20: Quanto em 5 anos? | C20: =FV(taxa_mensal,A20*12,aporte*-1) -> 24111.031 | D20: =C20*rendimento_carteira -> 229.05479
A21: 10 | B21: Quanto em 10 anos? | C21: =FV(taxa_mensal,A21*12,aporte*-1) -> 66631.218 | D21: =C21*rendimento_carteira -> 632.99657
A22: 20 | B22: Quanto em 20 anos? | C22: =FV(taxa_mensal,A22*12,aporte*-1) -> 273853.55 | D22: =C22*rendimento_carteira -> 2601.6087
A23: 30 | B23: Quanto em 30 anos? | C23: =FV(taxa_mensal,A23*12,aporte*-1) -> 918312.62 | D23: =C23*rendimento_carteira -> 8723.9698
B25: PERFIL DO INVESTIDOR
B26: Perfil escolhido | C26: Moderado
B27: Valor mensal a investir (R$) | C27: =aporte -> 300
B29: TIPO DE FII | C29: Percentual Sugerido | D29: Valor (R$)
B30: PAPEL | C30: =VLOOKUP($C$26&"-"&B30,Apoio!$A:$D,4,FALSE()) -> 0.25 | D30: =C30*$C$27 -> 75
B31: TIJOLO | C31: =VLOOKUP($C$26&"-"&B31,Apoio!$A:$D,4,FALSE()) -> 0.3 | D31: =C31*$C$27 -> 90
B32: HÍBRIDOS | C32: =VLOOKUP($C$26&"-"&B32,Apoio!$A:$D,4,FALSE()) -> 0.15 | D32: =C32*$C$27 -> 45
B33: FOFs | C33: =VLOOKUP($C$26&"-"&B33,Apoio!$A:$D,4,FALSE()) -> 0.1 | D33: =C33*$C$27 -> 30
B34: DESENVOLVIMENTO | C34: =VLOOKUP($C$26&"-"&B34,Apoio!$A:$D,4,FALSE()) -> 0.1 | D34: =C34*$C$27 -> 30
B35: HOTELARIA | C35: =VLOOKUP($C$26&"-"&B35,Apoio!$A:$D,4,FALSE()) -> 0.1 | D35: =C35*$C$27 -> 30
B36: TOTAL | C36: =SUM(C30:C35) -> 1 | D36: =SUM(D30:D35) -> 300

Sheet Apoio
A1: CHAVE | B1: PERFIL | C1: TIPO DE FII | D1: %
A2: =B2&"-"&C2 -> Conservador-PAPEL | B2: Conservador | C2: PAPEL | D2: 0.4
A3: =B3&"-"&C3 -> Conservador-TIJOLO | B3: Conservador | C3: TIJOLO | D3: 0.4
A4: =B4&"-"&C4 -> Conservador-HÍBRIDOS | B4: Conservador | C4: HÍBRIDOS | D4: 0.1
A5: =B5&"-"&C5 -> Conservador-FOFs | B5: Conservador | C5: FOFs | D5: 0.1
A6: =B6&"-"&C6 -> Conservador-DESENVOLVIMENTO | B6: Conservador | C6: DESENVOLVIMENTO | D6: 0
A7: =B7&"-"&C7 -> Conservador-HOTELARIA | B7: Conservador | C7: HOTELARIA | D7: 0
A8: =B8&"-"&C8 -> Moderado-PAPEL | B8: Moderado | C8: PAPEL | D8: 0.25
A9: =B9&"-"&C9 -> Moderado-TIJOLO | B9: Moderado | C9: TIJOLO | D9: 0.3
A10: =B10&"-"&C10 -> Moderado-HÍBRIDOS | B10: Moderado | C10: HÍBRIDOS | D10: 0.15
A11: =B11&"-"&C11 -> Moderado-FOFs | B11: Moderado | C11: FOFs | D11: 0.1
A12: =B12&"-"&C12 -> Moderado-DESENVOLVIMENTO | B12: Moderado | C12: DESENVOLVIMENTO | D12: 0.1
A13: =B13&"-"&C13 -> Moderado-HOTELARIA | B13: Moderado | C13: HOTELARIA | D13: 0.1
... A19: =B19&"-"&C19 -> Arrojado-HOTELARIA | B19: Arrojado | C19: HOTELARIA | D19: 0.25
A21: Verificação: soma de cada perfil deve ser 100%
A22: Soma Conservador | B22: =SUM(D2:D7) -> 1
A23: Soma Moderado | B23: =SUM(D8:D13) -> 1
A24: Soma Arrojado | B24: =SUM(D14:D19) -> 1
